ZetcodeSpringJiaochengChuyiFix1/README.md
ZetcodeSpringJiaochengChuyiFix1/__init__.py
ZetcodeSpringJiaochengChuyiFix1/__main__.py
ZetcodeSpringJiaochengChuyiFix1/file.epub
ZetcodeSpringJiaochengChuyiFix1/index.html
ZetcodeSpringJiaochengChuyiFix1/css/__init__.py
ZetcodeSpringJiaochengChuyiFix1/css/annotations.css
ZetcodeSpringJiaochengChuyiFix1/css/main.css
ZetcodeSpringJiaochengChuyiFix1/css/normalize.css
ZetcodeSpringJiaochengChuyiFix1/css/popup.css
ZetcodeSpringJiaochengChuyiFix1/font/__init__.py
ZetcodeSpringJiaochengChuyiFix1/font/fontello.eot
ZetcodeSpringJiaochengChuyiFix1/font/fontello.svg
ZetcodeSpringJiaochengChuyiFix1/font/fontello.ttf
ZetcodeSpringJiaochengChuyiFix1/font/fontello.woff
ZetcodeSpringJiaochengChuyiFix1/img/__init__.py
ZetcodeSpringJiaochengChuyiFix1/img/annotator-glyph-sprite.png
ZetcodeSpringJiaochengChuyiFix1/img/annotator-icon-sprite.png
ZetcodeSpringJiaochengChuyiFix1/img/apple-touch-icon.png
ZetcodeSpringJiaochengChuyiFix1/img/cancelfullscreen.png
ZetcodeSpringJiaochengChuyiFix1/img/close.png
ZetcodeSpringJiaochengChuyiFix1/img/fullscreen.png
ZetcodeSpringJiaochengChuyiFix1/img/loader.gif
ZetcodeSpringJiaochengChuyiFix1/img/menu-icon.png
ZetcodeSpringJiaochengChuyiFix1/img/save.png
ZetcodeSpringJiaochengChuyiFix1/img/saved.png
ZetcodeSpringJiaochengChuyiFix1/img/settings-s.png
ZetcodeSpringJiaochengChuyiFix1/img/settings.png
ZetcodeSpringJiaochengChuyiFix1/img/star.png
ZetcodeSpringJiaochengChuyiFix1/js/__init__.py
ZetcodeSpringJiaochengChuyiFix1/js/epub.js
ZetcodeSpringJiaochengChuyiFix1/js/epub.min.js
ZetcodeSpringJiaochengChuyiFix1/js/epub.min.map
ZetcodeSpringJiaochengChuyiFix1/js/hooks.min.js
ZetcodeSpringJiaochengChuyiFix1/js/hooks.min.map
ZetcodeSpringJiaochengChuyiFix1/js/reader.js
ZetcodeSpringJiaochengChuyiFix1/js/reader.js.map
ZetcodeSpringJiaochengChuyiFix1/js/reader.min.js
ZetcodeSpringJiaochengChuyiFix1/js/reader.min.map
ZetcodeSpringJiaochengChuyiFix1/js/hooks/__init__.py
zetcode_spring_jiaocheng_chuyi_fix1-2025.3.23.0.dist-info/METADATA
zetcode_spring_jiaocheng_chuyi_fix1-2025.3.23.0.dist-info/WHEEL
zetcode_spring_jiaocheng_chuyi_fix1-2025.3.23.0.dist-info/entry_points.txt
zetcode_spring_jiaocheng_chuyi_fix1-2025.3.23.0.dist-info/top_level.txt
zetcode_spring_jiaocheng_chuyi_fix1-2025.3.23.0.dist-info/RECORD
